redash_mcp/__init__.py
redash_mcp/api.py
redash_mcp/config.py
redash_mcp/server.py
redash_mcp/viz.py
redash_mcp-0.1.4.dist-info/METADATA
redash_mcp-0.1.4.dist-info/WHEEL
redash_mcp-0.1.4.dist-info/entry_points.txt
redash_mcp-0.1.4.dist-info/licenses/LICENSE
redash_mcp-0.1.4.dist-info/RECORD
