Metadata-Version: 2.4
Name: redash-mcp
Version: 0.1.4
Summary: Model Context Protocol (MCP) server for Redash - manage queries, dashboards, and visualizations
Project-URL: Homepage, https://github.com/wise-toddler/redash-mcp
Project-URL: Repository, https://github.com/wise-toddler/redash-mcp
Project-URL: Issues, https://github.com/wise-toddler/redash-mcp/issues
Author-email: Shivansh Singh <wiseeldrich2004@gmail.com>
License-Expression: MIT
License-File: LICENSE
Keywords: ai,claude,dashboard,mcp,model-context-protocol,redash,visualization
Classifier: Development Status :: 4 - Beta
Classifier: Intended Audience :: Developers
Classifier: License :: OSI Approved :: MIT License
Classifier: Programming Language :: Python :: 3
Classifier: Programming Language :: Python :: 3.10
Classifier: Programming Language :: Python :: 3.11
Classifier: Programming Language :: Python :: 3.12
Requires-Python: >=3.10
Requires-Dist: requests>=2.28.0
